setup.cfg
setup.py
tweetsearcher/__init__.py
tweetsearcher/proxy.py
tweetsearcher/searcher.py
tweetsearcher/tweet.py
tweetsearcher.egg-info/PKG-INFO
tweetsearcher.egg-info/SOURCES.txt
tweetsearcher.egg-info/dependency_links.txt
tweetsearcher.egg-info/requires.txt
tweetsearcher.egg-info/top_level.txt