Metadata-Version: 1.1
Name: tweetsearcher
Version: 1.4
Summary: Library to bypass limitations of the Twitter Official API
Home-page: https://github.com/alexanderhudym/tweet-searcher
Author: Alexander Hudym
Author-email: alexanderhudym@gmail.com
License: UNKNOWN
Download-URL: https://github.com/alexanderhudym/tweet-searcher/archive/1.0.tar.gz
Keywords: tweet,twitter,search,old
Platform: UNKNOWN
